{
  "metadata": {
    "description": "D&D 3.5 SRD Monster/Bestiary List",
    "source": "d20srd.org",
    "generatedDate": "2026-02-08"
  },
  "monsters": [
    "Aasimar", "Aboleth", "Aboleth Mage", "Abyssal Greater Basilisk", "Achaierai",
    "Air Elemental", "Air Mephit", "Allip", "Androsphinx", "Angel", "Animated Object",
    "Ankheg", "Annis", "Ape", "Aquatic Elf", "Aranea", "Archon", "Arrowhawk",
    "Assassin Vine", "Astral Deva", "Athach", "Avoral", "Azer",
    "Babau", "Baboon", "Badger", "Balor", "Barbed Devil", "Barghest", "Basilisk",
    "Bat", "Bat Swarm", "Bear (Black)", "Bear (Brown)", "Bear (Polar)",
    "Bearded Devil", "Bebilith", "Behir", "Belker", "Bison",
    "Black Dragon", "Black Pudding", "Blink Dog", "Blue Dragon", "Boar", "Bodak",
    "Bone Devil", "Bralani", "Brass Dragon", "Bronze Dragon", "Bugbear", "Bulette",
    "Camel", "Cat", "Cauchemar", "Celestial Charger", "Celestial Creature",
    "Centaur", "Centipede Swarm", "Chain Devil", "Chaos Beast", "Cheetah",
    "Chimera", "Choker", "Chuul", "Clay Golem", "Cloaker", "Cloud Giant",
    "Cockatrice", "Copper Dragon", "Couatl", "Criosphinx", "Crocodile",
    "Crocodile (Giant)", "Cryohydra",
    "Dark Naga", "Darkmantle", "Deep Dwarf", "Deep Halfling", "Deinonychus",
    "Delver", "Demon", "Derro", "Destrachan", "Devourer", "Devil", "Digester",
    "Dinosaur", "Dire Ape", "Dire Badger", "Dire Bat", "Dire Bear", "Dire Boar",
    "Dire Lion", "Dire Rat", "Dire Shark", "Dire Tiger", "Dire Weasel", "Dire Wolf",
    "Dire Wolverine", "Djinni", "Dog", "Dog (Riding)", "Donkey", "Doppelganger",
    "Dragon Turtle", "Dragon (True)", "Dragonne", "Dretch", "Drider", "Drow", "Dryad",
    "Duergar", "Dust Mephit", "Dwarf",
    "Eagle", "Eagle (Giant)", "Earth Elemental", "Earth Mephit", "Efreeti",
    "Elasmosaurus", "Elder Black Pudding", "Elemental", "Elephant", "Elf", "Erinyes",
    "Ethereal Filcher", "Ethereal Marauder", "Ettercap", "Ettin",
    "Fiendish Creature", "Fire Elemental", "Fire Giant", "Fire Mephit", "Flesh Golem",
    "Forest Gnome", "Formian", "Formian Myrmarch", "Formian Queen", "Formian Taskmaster",
    "Formian Warrior", "Formian Worker", "Frost Giant", "Frost Giant Jarl", "Frost Worm",
    "Fungus",
    "Gargoyle", "Gelatinous Cube", "Genie", "Ghaele", "Ghost", "Ghast", "Ghoul",
    "Giant", "Giant Ant", "Giant Bee", "Giant Bombardier Beetle", "Giant Fire Beetle",
    "Giant Praying Mantis", "Giant Stag Beetle", "Giant Wasp", "Gibbering Mouther",
    "Girallon", "Glabrezu", "Gnoll", "Gnome", "Goblin", "Gold Dragon", "Golem",
    "Golden Protector", "Gorgon", "Gray Elf", "Gray Ooze", "Gray Render",
    "Greater Barghest", "Greater Shadow", "Greater Stone Golem", "Green Dragon",
    "Green Hag", "Grick", "Griffon", "Grig", "Grimlock", "Guardian Naga", "Gynosphinx",
    "Hag", "Half-Celestial", "Half-Dragon", "Half-Elf", "Half-Fiend", "Half-Orc",
    "Halfling", "Harpy", "Harpy Archer", "Hawk", "Hell Hound", "Hellcat",
    "Hellwasp Swarm", "Hezrou", "Hieracosphinx", "Hill Giant",
    "Hill Giant Dire Wereboar", "Hippogriff", "Hobgoblin", "Homunculus",
    "Horned Devil", "Horse", "Horse (Heavy)", "Horse (Light)", "Hound Archon",
    "Hound Archon Hero", "Howler", "Hydra", "Hyena",
    "Ice Devil", "Ice Mephit", "Imp", "Inevitable", "Invisible Stalker", "Iron Golem",
    "Janni",
    "Kapoacinth", "Kobold", "Kolyarut", "Kraken", "Krenshar",
    "Lacedon", "Lamia", "Lammasu", "Lantern Archon", "Lemure", "Leonal", "Leopard",
    "Lich", "Lillend", "Lion", "Lizard", "Lizard (Monitor)", "Lizardfolk", "Locathah",
    "Locust Swarm", "Lycanthrope",
    "Magma Mephit", "Magmin", "Malenti", "Manta Ray", "Manticore", "Marilith",
    "Marut", "Medusa", "Megaraptor", "Mephit", "Merfolk", "Merrow", "Mimic",
    "Minotaur", "Mohrg", "Monkey", "Monster Centipede", "Monstrous Scorpion",
    "Monstrous Spider", "Mountain Dwarf", "Mule", "Mummy", "Mummy Lord",
    "Naga", "Nalfeshnee", "Nessian Warhound", "Night Hag", "Nightcrawler",
    "Nightmare", "Nightshade", "Nightwalker", "Nightwing", "Nixie", "Noble Djinn", "Nymph",
    "Ochre Jelly", "Octopus", "Octopus (Giant)", "Ogre", "Ogre Barbarian",
    "Ogre Mage", "Ooze", "Ooze Mephit", "Orc", "Otyugh", "Owl", "Owl (Giant)", "Owlbear",
    "Pegasus", "Phantom Fungus", "Phase Spider", "Phasm", "Pit Fiend", "Pixie",
    "Planetar", "Planetouched", "Pony", "Pony (War)", "Porpoise", "Pseudodragon",
    "Purple Worm", "Pyrohydra",
    "Quasit",
    "Rakshasa", "Rast", "Rat", "Rat Swarm", "Raven", "Ravid", "Razor Boar",
    "Red Dragon", "Remorhaz", "Retriever", "Rhinoceros", "Roc", "Roper", "Rust Monster",
    "Sahuagin", "Sahuagin Mutants", "Salamander", "Salt Mephit", "Satyr",
    "Scorpionfolk", "Scrag", "Sea Cat", "Sea Hag", "Shadow", "Shadow Mastiff",
    "Shambling Mound", "Shark", "Shield Guardian", "Shrieker", "Shocker Lizard",
    "Skeleton", "Skum", "Snake", "Snake (Constrictor)", "Snake (Viper)", "Solar",
    "Spectre", "Sphinx", "Spider Eater", "Spider Swarm", "Spirit Naga", "Sprite",
    "Squid", "Squid (Giant)", "Steam Mephit", "Stirge", "Stone Giant",
    "Stone Giant Elders", "Stone Golem", "Storm Giant", "Succubus", "Svirfneblin", "Swarm",
    "Tallfellow Halfling", "Tarrasque", "Tendriculos", "Thoqqua", "Tiefling", "Tiger",
    "Titan", "Toad", "Tojanida", "Treant", "Triceratops", "Triton", "Troglodyte",
    "Troll", "Troll Hunter", "Trumpet Archon", "Tyrannosaurus",
    "Unicorn",
    "Vampire", "Vampire Spawn", "Vargouille", "Violet Fungus", "Vrock",
    "Water Elemental", "Water Mephit", "Water Naga", "Weasel", "Werebear", "Wereboar",
    "Wererat", "Weretiger", "Werewolf", "Werewolf Lord", "Whale", "White Dragon",
    "Wight", "Wild Elf", "Will-O'-Wisp", "Winter Wolf", "Wolf", "Wood Elf",
    "Wolverine", "Worg", "Wraith", "Wyvern",
    "Xill", "Xorn",
    "Yeth Hound", "Yrthak",
    "Zelekhut", "Zombie"
  ]
}
